hand_gesture_recognizer/__init__.py
hand_gesture_recognizer/custom_gestures.py
hand_gesture_recognizer/main.py
hand_gesture_recognizer-1.3.1.dist-info/METADATA
hand_gesture_recognizer-1.3.1.dist-info/WHEEL
hand_gesture_recognizer-1.3.1.dist-info/top_level.txt
hand_gesture_recognizer-1.3.1.dist-info/RECORD
